nonebot_plugin_bind/__init__.py
nonebot_plugin_bind/_types.py
nonebot_plugin_bind/config.py
nonebot_plugin_bind/group_sql.py
nonebot_plugin_bind/migrations/57ff5da24acb_init_db.py
nonebot_plugin_bind/user_sql.py
nonebot_plugin_bind/utils.py
nonebot_plugin_bind-0.2.2.dist-info/METADATA
nonebot_plugin_bind-0.2.2.dist-info/WHEEL
nonebot_plugin_bind-0.2.2.dist-info/RECORD
