Metadata-Version: 2.1
Name: nonebot-plugin-bind
Version: 0.2.2
Summary: nonebot多平台账户信息绑定
Home-page: https://github.com/canxin121/nonebot_plugin_bind
Author: canxin
Author-email: 1969730106@qq.com
Requires-Python: >=3.8,<4.0
Classifier: Programming Language :: Python :: 3
Classifier: Programming Language :: Python :: 3.8
Classifier: Programming Language :: Python :: 3.9
Classifier: Programming Language :: Python :: 3.10
Classifier: Programming Language :: Python :: 3.11
Requires-Dist: nonebot-plugin-alconna (>=0.27.2)
Requires-Dist: nonebot-plugin-apscheduler (>=0.3.0)
Requires-Dist: nonebot-plugin-datastore (>=1.1.0)
Requires-Dist: nonebot2 (>=2.0.1,<3.0.0)
